odoo8_addon_product_variant_search_by_attribute-8.0.1.0.0.99.dev15-nspkg.pth
odoo_addons/product_variant_search_by_attribute/README.rst
odoo_addons/product_variant_search_by_attribute/__init__.py
odoo_addons/product_variant_search_by_attribute/__openerp__.py
odoo_addons/product_variant_search_by_attribute/data/config_data.xml
odoo_addons/product_variant_search_by_attribute/i18n/ca.po
odoo_addons/product_variant_search_by_attribute/i18n/de.po
odoo_addons/product_variant_search_by_attribute/i18n/el_GR.po
odoo_addons/product_variant_search_by_attribute/i18n/es.po
odoo_addons/product_variant_search_by_attribute/i18n/es_ES.po
odoo_addons/product_variant_search_by_attribute/i18n/eu.po
odoo_addons/product_variant_search_by_attribute/i18n/fi.po
odoo_addons/product_variant_search_by_attribute/i18n/fr.po
odoo_addons/product_variant_search_by_attribute/i18n/fr_CH.po
odoo_addons/product_variant_search_by_attribute/i18n/fr_FR.po
odoo_addons/product_variant_search_by_attribute/i18n/gl.po
odoo_addons/product_variant_search_by_attribute/i18n/hr.po
odoo_addons/product_variant_search_by_attribute/i18n/hr_HR.po
odoo_addons/product_variant_search_by_attribute/i18n/it.po
odoo_addons/product_variant_search_by_attribute/i18n/nl.po
odoo_addons/product_variant_search_by_attribute/i18n/nl_NL.po
odoo_addons/product_variant_search_by_attribute/i18n/product_variant_search_by_attribute.pot
odoo_addons/product_variant_search_by_attribute/i18n/pt.po
odoo_addons/product_variant_search_by_attribute/i18n/pt_BR.po
odoo_addons/product_variant_search_by_attribute/i18n/ro.po
odoo_addons/product_variant_search_by_attribute/i18n/ru.po
odoo_addons/product_variant_search_by_attribute/i18n/sk.po
odoo_addons/product_variant_search_by_attribute/i18n/sl.po
odoo_addons/product_variant_search_by_attribute/i18n/tr.po
odoo_addons/product_variant_search_by_attribute/i18n/tr_TR.po
odoo_addons/product_variant_search_by_attribute/i18n/vi_VN.po
odoo_addons/product_variant_search_by_attribute/i18n/zh_CN.po
odoo8_addon_product_variant_search_by_attribute-8.0.1.0.0.99.dev15.dist-info/METADATA
odoo8_addon_product_variant_search_by_attribute-8.0.1.0.0.99.dev15.dist-info/WHEEL
odoo8_addon_product_variant_search_by_attribute-8.0.1.0.0.99.dev15.dist-info/namespace_packages.txt
odoo8_addon_product_variant_search_by_attribute-8.0.1.0.0.99.dev15.dist-info/top_level.txt
odoo8_addon_product_variant_search_by_attribute-8.0.1.0.0.99.dev15.dist-info/RECORD
