Metadata-Version: 2.1
Name: odoo8-addon-product-variant-search-by-attribute
Version: 8.0.1.0.0.99.dev15
Summary: Allows searching inside the product variant attributes all attributes at once with multiple keywords
Home-page: http://www.akretion.com/
Author: Akretion, Odoo Community Association (OCA)
Author-email: support@odoo-community.org
License: AGPL-3
Platform: UNKNOWN
Classifier: Programming Language :: Python
Classifier: Framework :: Odoo
Classifier: License :: OSI Approved :: GNU Affero General Public License v3
Requires-Python: ~=2.7
Requires-Dist: odoo (<9.0a,>=8.0a)
